mylib/__init__.py
mylib/mymodule12222221112222.py
tests/__init__.py
tests/test_mymodule.py
mylibrary122222111222-0.1.dist-info/METADATA
mylibrary122222111222-0.1.dist-info/WHEEL
mylibrary122222111222-0.1.dist-info/top_level.txt
mylibrary122222111222-0.1.dist-info/RECORD
