Metadata-Version: 2.1
Name: mylibrary122222111222
Version: 0.1
Summary: Простая библиотека для математических операций
Home-page: https://github.com/ваш_репозиторий
Author: Ваше Имя
Author-email: ваш_email@example.com
